directory_proxy/__init__.py
directory_proxy/helpers.py
directory_proxy/views.py
directory_proxy/conf/__init__.py
directory_proxy/conf/settings.py
directory_proxy/conf/urls.py
directory_proxy/conf/wsgi.py
directory_proxy-0.1.0.dist-info/LICENSE
directory_proxy-0.1.0.dist-info/METADATA
directory_proxy-0.1.0.dist-info/WHEEL
directory_proxy-0.1.0.dist-info/top_level.txt
directory_proxy-0.1.0.dist-info/RECORD
