Metadata-Version: 2.1
Name: directory-proxy
Version: 0.1.0
Summary: Proxy
Home-page: https://github.com/uktrade/directory-proxy
Author: Department for International Trade
License: MIT
Platform: UNKNOWN
Classifier: Development Status :: 5 - Production/Stable
Classifier: Environment :: Web Environment
Classifier: Framework :: Django
Classifier: Framework :: Django :: 1.11
Classifier: Intended Audience :: Developers
Classifier: License :: OSI Approved :: MIT License
Classifier: Natural Language :: English
Classifier: Operating System :: OS Independent
Classifier: Programming Language :: Python :: 3.5
Classifier: Programming Language :: Python :: 3.6
Classifier: Programming Language :: Python :: Implementation :: PyPy
Classifier: Topic :: Software Development :: Libraries :: Python Modules
Requires-Dist: django (<2.0a1,>=1.11.15)
Requires-Dist: django-revproxy (<1.0.0,>=0.9.15)
Requires-Dist: django-environ (<1.0.0,>=0.4.5)
Requires-Dist: gunicorn (<20.0.0,>=19.9.0)
Requires-Dist: raven (<7.0.0,>=6.10.0)
Requires-Dist: sigauth (<5.0.0,>=4.0.1)
Requires-Dist: directory-components (<4.0.0,>=3.5.0)
Provides-Extra: test
Requires-Dist: pytest (==4.0.2) ; extra == 'test'
Requires-Dist: pytest-cov (==2.6.0) ; extra == 'test'
Requires-Dist: pytest-sugar (==0.9.2) ; extra == 'test'
Requires-Dist: pytest-django (==3.4.4) ; extra == 'test'
Requires-Dist: flake8 (==3.6.0) ; extra == 'test'
Requires-Dist: codecov (==2.0.15) ; extra == 'test'
Requires-Dist: requests-mock (==1.5.2) ; extra == 'test'
Requires-Dist: twine (<2.0.0,>=1.11.0) ; extra == 'test'
Requires-Dist: wheel (<1.0.0,>=0.31.0) ; extra == 'test'
Requires-Dist: setuptools (<39.0.0,>=38.6.0) ; extra == 'test'
